{
  "kind": "collectionType",
  "collectionName": "lyrics",
  "info": {
    "singularName": "lyric",
    "pluralName": "lyrics",
    "displayName": "Lyric",
    "description": ""
  },
  "options": {
    "draftAndPublish": true
  },
  "attributes": {
    "name": {
      "type": "string",
      "required": true
    },
    "name_py": {
      "type": "string",
      "required": true
    },
    "lyrics": {
      "type": "text",
      "required": true
    },
    "lyrics_py": {
      "type": "text",
      "required": true
    },
    "author": {
      "type": "string",
      "required": true
    },
    "author_py": {
      "type": "string",
      "required": true
    },
    "cover": {
      "allowedTypes": [
        "images"
      ],
      "type": "media",
      "multiple": false,
      "required": true
    }
  }
}
